ChatBMS/__init__.py
ChatBMS/chat_completions.py
chatbms-0.0.2.dist-info/METADATA
chatbms-0.0.2.dist-info/WHEEL
chatbms-0.0.2.dist-info/licenses/LICENSE
chatbms-0.0.2.dist-info/RECORD
