Metadata-Version: 2.1
Name: ChatBMS
Version: 0.0.2
Summary: API Wrapper for ChatBMS API
Project-URL: Homepage, https://ChatBMS.in
Project-URL: Bug Tracker, https://ChatBMS.in/issues
Author-email: Chirag Manjeshwar <chirunder@gmail.com>
License-File: LICENSE
Classifier: License :: OSI Approved :: MIT License
Classifier: Operating System :: OS Independent
Classifier: Programming Language :: Python :: 3
Requires-Python: >=3.0
